Workbook

Sheet 使い方
A1: eBay輸出 利益計算・リサーチシート
A3: セルの色
B4: 青字・黄色背景 … 入力するセル
B5: 黒字・白背景 … 自動計算（触らない）
B6: 灰色背景 … 計算用の補助セル（触らない）
A8: 使う順番
B9: 1. 「設定」… 為替レートを今日の値に更新。手数料率・関税率は eBay 公式で確認して直す（最初に1回、あとは月1回）
B10: 2. 「送料表」… 仮の値が入っています。SpeedPAK Economy の公式料金で必ず上書きする
B11: 3. 「ショップ分析」… ① 売れている日本人セラーを3〜5店記録し、共通点をまとめる
B12: 4. 「候補展開」… ② 1つの売れ筋を横・縦・周辺に20〜30件広げ、③ 売れた理由が同じものに○を付ける
B13: 5. 「利益計算」… ○の候補を転記。判定が「◎ 出品候補」のものだけ出品する
B14: 「目標を満たす最低販売価格」の列で、いくらで売れれば合格かが分かる（相場がそれより下なら見送り）
B15: 6. 「実績記録」… 毎日の作業時間・出品数・販売数・利益を記録。月ごとの時給を見る
A17: 判定の基準（「設定」で変更できる）
B18: ◎ 出品候補 … 利益率20%以上 かつ 利益1,000円以上 かつ 直近90日に3件以上売れている
B19: △ 利益OK・販売実績が不足 … 利益は出るが売れた実績が少ない。様子見
B20: × 見送り … 利益率か利益額が足りない
A22: 計算の前提と注意
B23: ・利益 = 売上 −（仕入れ値 + 仕入れ時の送料 + eBay手数料 + 換金コスト + 国際送料 + 関税など + 梱包資材費）
B24: ・eBay手数料 =（販売価格 + 買い手負担の送料）×（落札手数料率 + 海外決済手数料率 + 広告費率）+ 1注文あたり固定手数料
B25: ・関税は売り手負担（DDP）前提の保守的な計算。英国・EU・オーストラリアの付加価値税（GST）は eBay が買い手から徴収するので含めていない
B26: ・米国では売上税込みの金額に落札手数料がかかるため、実際の手数料は計算より少し高くなる
B27: ・手数料率・関税率・送料は変わります。数値は2026年10月時点の目安なので、作業前に公式情報で確認してください
A29: 出典
B30: eBay 販売手数料の概要：https://wwwcojp.ebay.com/fee/overview-selling-fees
B31: eBay 米国関税に関する案内：https://wwwcojp2.ebay.com/tariffs
B32: eBay DDP（関税元払い）案内：https://wwwcojp.ebay.com/ddp-info
B33: SpeedPAK Economy の概要（ネットショップ担当者フォーラム）：https://netshop.impress.co.jp/node/12664
B34: 日本郵便 米国宛て郵便物の引受再開（2026年4月）：https://www.post.japanpost.jp/int/information/2026/0413_01.html

Sheet 設定
A1: 設定（為替・手数料・関税・判定基準）
A2: 青字・黄色のセルを最新の値に更新してください。灰色は自動計算です。数値は2026年10月時点の目安で、必ず公式情報で確認してください。
A3: 項目 | C3: 値 | D3: 単位 | E3: 説明・出典
A4: 為替レート（円/ドル） | C4: 150 | D4: 円 | E4: 仮の値。作業する日のレートに更新する。
A5: 為替レート（円/ユーロ） | C5: 165 | D5: 円 | E5: 仮の値。EU向けの固定関税（€3）の円換算に使う。
A6: eBay 落札手数料率 | C6: 0.1325 | D6: % | E6: 多くのカテゴリーの標準料率を仮置き。カテゴリー・ストア有無で変わる。米国では売上税込みの金額にかかるため、実際は少し高くなる。要確認：eBay公式「販売手数料の概要」
A7: eBay 海外決済手数料率 | C7: 0.0165 | D7: % | E7: International fee。日本セラー（グローバルセラー）に適用。要確認：eBay公式「販売手数料の概要」
A8: 1注文あたり固定手数料 | C8: 0.4 | D8: $ | E8: Per-order fee。注文金額により変わる。要確認。
A9: 広告費率（Promoted Listings） | C9: 0 | D9: % | E9: 広告を使う場合だけ入力（例：2〜5%）。使わなければ 0。
A10: 換金コスト率（ドル→円） | C10: 0.02 | D10: % | E10: 売上を円で受け取るときの為替コストの仮置き。受取方法（eBay直接／Payoneer等）で変わる。
A11: 梱包資材費（1件あたり） | C11: 100 | D11: 円 | E11: 緩衝材・袋・テープなど。段ボールを再利用するなら下げてよい。
A12: 目標利益率 | C12: 0.2 | D12: % | E12: これ以上なら出品候補。計画の基準は 20%。
A13: 最低利益額（1件あたり） | C13: 1000 | D13: 円 | E13: これ未満は手間に見合わないので見送り。
A14: 最低販売実績（直近90日） | C14: 3 | D14: 件 | E14: Product Research（Terapeak）で確認した販売数の基準。
A15: （自動）手数料・換金後に残る率 | C15: =(1-($C$6+$C$7+$C$9))*(1-$C$10) -> 0.83398 | E15: 最低販売価格の計算に使う。触らない。
A16: （自動）上の率 − 目標利益率 | C16: =$C$15-$C$12 -> 0.63398 | E16: 最低販売価格の計算に使う。触らない。
A18: 発送先別の関税・前払い手数料
A19: 発送先コード | B19: 国名 | C19: 関税率（商品代に対して） | D19: 固定関税（円） | E19: 前払い・通関手数料（円） | F19: 備考
A20: US | B20: 米国 | C20: 0.15 | D20: 0 | E20: 0 | F20: 日本からの商品にかかる関税率を仮置き（2025年の日米合意の相互関税率）。売り手負担（DDP）前提。最新の率と前払い手数料は eBay「米国関税に関する案内」で要確認。
A21: UK | B21: 英国 | C21: 0 | D21: 0 | E21: 0 | F21: £135以下の付加価値税は eBay が購入時に買い手から徴収するので計算に含めない。
A22: DE | B22: ドイツ（EU） | C22: 0 | D22: =設定!$C$5*3 -> 495 | E22: 0 | F22: 2026年7月から€150以下の荷物にも品目ごとに€3の関税。保守的に売り手負担で計算。付加価値税は eBay が買い手から徴収。
A23: AU | B23: オーストラリア | C23: 0 | D23: 0 | E23: 0 | F23: AUD1,000以下のGSTは eBay が購入時に買い手から徴収するので計算に含めない。
A25: 売れた理由タグ（プルダウンの選択肢。自由に書き換え・追加してよい）
A26: キャラクター人気
A27: 日本限定
A28: ブランド人気
A29: 海外で入手困難
A30: サイズ・容量がちょうどいい
A31: セット内容がいい
A32: ギフト需要
A33: 季節・イベント
A34: 消耗品（リピート）
A35: その他

Sheet 送料表
A1: 国際送料表（SpeedPAK Economy 想定）
A2: 【重要】下の料金はすべて仮の値です（国別の差も未反映）。eBay 公式の SpeedPAK Economy 料金表で上書きしてください。
A4: 重量下限（g） | B4: 重量上限（g） | C4: US | D4: UK | E4: DE | F4: AU
A5: 0 | B5: 100 | C5: 1150 | D5: 1150 | E5: 1150 | F5: 1150
A6: =B5+1 -> 101 | B6: 200 | C6: 1300 | D6: 1300 | E6: 1300 | F6: 1300
A7: =B6+1 -> 201 | B7: 300 | C7: 1450 | D7: 1450 | E7: 1450 | F7: 1450
A8: =B7+1 -> 301 | B8: 400 | C8: 1600 | D8: 1600 | E8: 1600 | F8: 1600
A9: =B8+1 -> 401 | B9: 500 | C9: 1750 | D9: 1750 | E9: 1750 | F9: 1750
A10: =B9+1 -> 501 | B10: 600 | C10: 1900 | D10: 1900 | E10: 1900 | F10: 1900
A11: =B10+1 -> 601 | B11: 700 | C11: 2050 | D11: 2050 | E11: 2050 | F11: 2050
A12: =B11+1 -> 701 | B12: 800 | C12: 2200 | D12: 2200 | E12: 2200 | F12: 2200
A13: =B12+1 -> 801 | B13: 900 | C13: 2350 | D13: 2350 | E13: 2350 | F13: 2350
A14: =B13+1 -> 901 | B14: 1000 | C14: 2500 | D14: 2500 | E14: 2500 | F14: 2500
A15: =B14+1 -> 1001 | B15: 1250 | C15: 2900 | D15: 2900 | E15: 2900 | F15: 2900
A16: =B15+1 -> 1251 | B16: 1500 | C16: 3300 | D16: 3300 | E16: 3300 | F16: 3300
A17: =B16+1 -> 1501 | B17: 1750 | C17: 3700 | D17: 3700 | E17: 3700 | F17: 3700
A18: =B17+1 -> 1751 | B18: 2000 | C18: 4100 | D18: 4100 | E18: 4100 | F18: 4100
A20: ・重量は梱包後の重さ（g）。上限を超える重さは「利益計算」で「範囲外」と表示されます。行を増やす場合は利益計算の数式の範囲も広げてください。
A21: ・出典：SpeedPAK Economy は「1,141円から」（ネットショップ担当者フォーラム 2024年8月の記事）。それ以外の数値は仮置き。

Sheet 利益計算
A1: 利益計算（1行 = 1商品）
A2: 青字・黄色のセルを入力すると、手数料・送料・関税を引いた利益と判定が出ます。No.1 の行は例（ツイートの水筒：3,300円 → 約9,000円）。
B3: ◎ 出品候補の件数 | C3: =COUNTIF(V5:V104,"◎*") -> 0
A4: No | B4: 商品名 | C4: 仕入れ先 | D4: 仕入れ値（円） | E4: 仕入れ時の送料など（円） | F4: 販売価格（$） | G4: 買い手負担の送料（$） 送料無料なら0 | H4: 発送先 | I4: 梱包後の重量（g） | J4: 直近90日の販売数（件） | K4: 売れた理由タグ | L4: 売上合計（円） | M4: eBay手数料（円） | N4: 換金コスト（円） | O4: 国際送料（円） | P4: 関税など（円） | Q4: 梱包資材費（円） | R4: 総コスト（円） | S4: 利益（円） | T4: 利益率 | U4: 目標を満たす最低販売価格（$） | V4: 判定 | W4: メモ | X4: （計算用）関税率 | Y4: （計算用）固定関税＋手数料（円）
A5: 1 | B5: 水筒（ツイートの例：3,300円 → 約9,000円） | C5: Amazon | D5: 3300 | E5: 0 | F5: 60 | G5: 0 | H5: US | I5: 450 | J5: 5 | K5: キャラクター人気 | L5: =IF(AND($D5<>"",$F5<>"",$H5<>"",$I5<>""),($F5+N($G5))*設定!$C$4,"") -> 9000 | M5: =IF($L5="","",(($F5+N($G5))*(設定!$C$6+設定!$C$7+設定!$C$9)+設定!$C$8)*設定!$C$4) -> 1401 | N5: =IF($L5="","",($L5-$M5)*設定!$C$10) -> 151.98 | O5: =IF($L5="","",IF($I5>MAX(送料表!$B$5:$B$18),"範囲外",INDEX(送料表!$C$5:$F$18,MATCH($I5,送料表!$A$5:$A$18,1),MATCH($H5,送料表!$C$4:$F$4,0)))) -> 1750 | P5: =IF($L5="","",$F5*設定!$C$4*$X5+$Y5) -> 1350 | Q5: =IF($L5="","",設定!$C$11) -> 100 | R5: =IF(OR($L5="",NOT(ISNUMBER($O5))),"",N($D5)+N($E5)+$M5+$N5+$O5+$P5+$Q5) -> 8052.98 | S5: =IF($R5="","",$L5-$R5) -> 947.02 | T5: =IF(OR($S5="",N($L5)=0),"",$S5/$L5) -> 0.10522444 | U5: =IF(OR($L5="",NOT(ISNUMBER($O5))),"",IF(設定!$C$16-$X5<=0,"設定を確認",MAX((設定!$C$8*設定!$C$4*(1-設定!$C$10)+$Y5+N($D5)+N($E5)+$O5+$Q5-N($G5)*設定!$C$4*設定!$C$16)/(設定!$C$4*(設定!$C$16-$X5)),(設定!$C$8*設定!$C$4*(1-設定!$C$10)+$Y5+N($D5)+N($E5)+$O5+$Q5+設定!$C$13-N($G5)*設定!$C$4*設定!$C$15)/(設定!$C$4*(設定!$C$15-$X5))))) -> 71.749521 | V5: =IF($L5="","",IF(NOT(ISNUMBER($O5)),"要確認：重量が送料表の範囲外",IF(AND($T5>=設定!$C$12,$S5>=設定!$C$13,N($J5)>=設定!$C$14),"◎ 出品候補",IF(AND($T5>=設定!$C$12,$S5>=設定!$C$13),"△ 利益OK・販売実績が不足","× 見送り")))) -> × 見送り | W5: 例の行。米国の関税と送料で利益が薄くなる。最低販売価格の列で、いくらなら合格かが分かる。 | X5: =IF($H5="","",INDEX(設定!$C$20:$C$23,MATCH($H5,設定!$A$20:$A$23,0))) -> 0.15 | Y5: =IF($H5="","",INDEX(設定!$D$20:$D$23,MATCH($H5,設定!$A$20:$A$23,0))+INDEX(設定!$E$20:$E$23,MATCH($H5,設定!$A$20:$A$23,0))) -> 0
A6: 2 | L6: =IF(AND($D6<>"",$F6<>"",$H6<>"",$I6<>""),($F6+N($G6))*設定!$C$4,"") | M6: =IF($L6="","",(($F6+N($G6))*(設定!$C$6+設定!$C$7+設定!$C$9)+設定!$C$8)*設定!$C$4) | N6: =IF($L6="","",($L6-$M6)*設定!$C$10) | O6: =IF($L6="","",IF($I6>MAX(送料表!$B$5:$B$18),"範囲外",INDEX(送料表!$C$5:$F$18,MATCH($I6,送料表!$A$5:$A$18,1),MATCH($H6,送料表!$C$4:$F$4,0)))) | P6: =IF($L6="","",$F6*設定!$C$4*$X6+$Y6) | Q6: =IF($L6="","",設定!$C$11) | R6: =IF(OR($L6="",NOT(ISNUMBER($O6))),"",N($D6)+N($E6)+$M6+$N6+$O6+$P6+$Q6) | S6: =IF($R6="","",$L6-$R6) | T6: =IF(OR($S6="",N($L6)=0),"",$S6/$L6) | U6: =IF(OR($L6="",NOT(ISNUMBER($O6))),"",IF(設定!$C$16-$X6<=0,"設定を確認",MAX((設定!$C$8*設定!$C$4*(1-設定!$C$10)+$Y6+N($D6)+N($E6)+$O6+$Q6-N($G6)*設定!$C$4*設定!$C$16)/(設定!$C$4*(設定!$C$16-$X6)),(設定!$C$8*設定!$C$4*(1-設定!$C$10)+$Y6+N($D6)+N($E6)+$O6+$Q6+設定!$C$13-N($G6)*設定!$C$4*設定!$C$15)/(設定!$C$4*(設定!$C$15-$X6))))) | V6: =IF($L6="","",IF(NOT(ISNUMBER($O6)),"要確認：重量が送料表の範囲外",IF(AND($T6>=設定!$C$12,$S6>=設定!$C$13,N($J6)>=設定!$C$14),"◎ 出品候補",IF(AND($T6>=設定!$C$12,$S6>=設定!$C$13),"△ 利益OK・販売実績が不足","× 見送り")))) | X6: =IF($H6="","",INDEX(設定!$C$20:$C$23,MATCH($H6,設定!$A$20:$A$23,0))) | Y6: =IF($H6="","",INDEX(設定!$D$20:$D$23,MATCH($H6,設定!$A$20:$A$23,0))+INDEX(設定!$E$20:$E$23,MATCH($H6,設定!$A$20:$A$23,0)))
A7: 3 | L7: =IF(AND($D7<>"",$F7<>"",$H7<>"",$I7<>""),($F7+N($G7))*設定!$C$4,"") | M7: =IF($L7="","",(($F7+N($G7))*(設定!$C$6+設定!$C$7+設定!$C$9)+設定!$C$8)*設定!$C$4) | N7: =IF($L7="","",($L7-$M7)*設定!$C$10) | O7: =IF($L7="","",IF($I7>MAX(送料表!$B$5:$B$18),"範囲外",INDEX(送料表!$C$5:$F$18,MATCH($I7,送料表!$A$5:$A$18,1),MATCH($H7,送料表!$C$4:$F$4,0)))) | P7: =IF($L7="","",$F7*設定!$C$4*$X7+$Y7) | Q7: =IF($L7="","",設定!$C$11) | R7: =IF(OR($L7="",NOT(ISNUMBER($O7))),"",N($D7)+N($E7)+$M7+$N7+$O7+$P7+$Q7) | S7: =IF($R7="","",$L7-$R7) | T7: =IF(OR($S7="",N($L7)=0),"",$S7/$L7) | U7: =IF(OR($L7="",NOT(ISNUMBER($O7))),"",IF(設定!$C$16-$X7<=0,"設定を確認",MAX((設定!$C$8*設定!$C$4*(1-設定!$C$10)+$Y7+N($D7)+N($E7)+$O7+$Q7-N($G7)*設定!$C$4*設定!$C$16)/(設定!$C$4*(設定!$C$16-$X7)),(設定!$C$8*設定!$C$4*(1-設定!$C$10)+$Y7+N($D7)+N($E7)+$O7+$Q7+設定!$C$13-N($G7)*設定!$C$4*設定!$C$15)/(設定!$C$4*(設定!$C$15-$X7))))) | V7: =IF($L7="","",IF(NOT(ISNUMBER($O7)),"要確認：重量が送料表の範囲外",IF(AND($T7>=設定!$C$12,$S7>=設定!$C$13,N($J7)>=設定!$C$14),"◎ 出品候補",IF(AND($T7>=設定!$C$12,$S7>=設定!$C$13),"△ 利益OK・販売実績が不足","× 見送り")))) | X7: =IF($H7="","",INDEX(設定!$C$20:$C$23,MATCH($H7,設定!$A$20:$A$23,0))) | Y7: =IF($H7="","",INDEX(設定!$D$20:$D$23,MATCH($H7,設定!$A$20:$A$23,0))+INDEX(設定!$E$20:$E$23,MATCH($H7,設定!$A$20:$A$23,0)))
A8: 4 | L8: =IF(AND($D8<>"",$F8<>"",$H8<>"",$I8<>""),($F8+N($G8))*設定!$C$4,"") | M8: =IF($L8="","",(($F8+N($G8))*(設定!$C$6+設定!$C$7+設定!$C$9)+設定!$C$8)*設定!$C$4) | N8: =IF($L8="","",($L8-$M8)*設定!$C$10) | O8: =IF($L8="","",IF($I8>MAX(送料表!$B$5:$B$18),"範囲外",INDEX(送料表!$C$5:$F$18,MATCH($I8,送料表!$A$5:$A$18,1),MATCH($H8,送料表!$C$4:$F$4,0)))) | P8: =IF($L8="","",$F8*設定!$C$4*$X8+$Y8) | Q8: =IF($L8="","",設定!$C$11) | R8: =IF(OR($L8="",NOT(ISNUMBER($O8))),"",N($D8)+N($E8)+$M8+$N8+$O8+$P8+$Q8) | S8: =IF($R8="","",$L8-$R8) | T8: =IF(OR($S8="",N($L8)=0),"",$S8/$L8) | U8: =IF(OR($L8="",NOT(ISNUMBER($O8))),"",IF(設定!$C$16-$X8<=0,"設定を確認",MAX((設定!$C$8*設定!$C$4*(1-設定!$C$10)+$Y8+N($D8)+N($E8)+$O8+$Q8-N($G8)*設定!$C$4*設定!$C$16)/(設定!$C$4*(設定!$C$16-$X8)),(設定!$C$8*設定!$C$4*(1-設定!$C$10)+$Y8+N($D8)+N($E8)+$O8+$Q8+設定!$C$13-N($G8)*設定!$C$4*設定!$C$15)/(設定!$C$4*(設定!$C$15-$X8))))) | V8: =IF($L8="","",IF(NOT(ISNUMBER($O8)),"要確認：重量が送料表の範囲外",IF(AND($T8>=設定!$C$12,$S8>=設定!$C$13,N($J8)>=設定!$C$14),"◎ 出品候補",IF(AND($T8>=設定!$C$12,$S8>=設定!$C$13),"△ 利益OK・販売実績が不足","× 見送り")))) | X8: =IF($H8="","",INDEX(設定!$C$20:$C$23,MATCH($H8,設定!$A$20:$A$23,0))) | Y8: =IF($H8="","",INDEX(設定!$D$20:$D$23,MATCH($H8,設定!$A$20:$A$23,0))+INDEX(設定!$E$20:$E$23,MATCH($H8,設定!$A$20:$A$23,0)))
A9: 5 | L9: =IF(AND($D9<>"",$F9<>"",$H9<>"",$I9<>""),($F9+N($G9))*設定!$C$4,"") | M9: =IF($L9="","",(($F9+N($G9))*(設定!$C$6+設定!$C$7+設定!$C$9)+設定!$C$8)*設定!$C$4) | N9: =IF($L9="","",($L9-$M9)*設定!$C$10) | O9: =IF($L9="","",IF($I9>MAX(送料表!$B$5:$B$18),"範囲外",INDEX(送料表!$C$5:$F$18,MATCH($I9,送料表!$A$5:$A$18,1),MATCH($H9,送料表!$C$4:$F$4,0)))) | P9: =IF($L9="","",$F9*設定!$C$4*$X9+$Y9) | Q9: =IF($L9="","",設定!$C$11) | R9: =IF(OR($L9="",NOT(ISNUMBER($O9))),"",N($D9)+N($E9)+$M9+$N9+$O9+$P9+$Q9) | S9: =IF($R9="","",$L9-$R9) | T9: =IF(OR($S9="",N($L9)=0),"",$S9/$L9) | U9: =IF(OR($L9="",NOT(ISNUMBER($O9))),"",IF(設定!$C$16-$X9<=0,"設定を確認",MAX((設定!$C$8*設定!$C$4*(1-設定!$C$10)+$Y9+N($D9)+N($E9)+$O9+$Q9-N($G9)*設定!$C$4*設定!$C$16)/(設定!$C$4*(設定!$C$16-$X9)),(設定!$C$8*設定!$C$4*(1-設定!$C$10)+$Y9+N($D9)+N($E9)+$O9+$Q9+設定!$C$13-N($G9)*設定!$C$4*設定!$C$15)/(設定!$C$4*(設定!$C$15-$X9))))) | V9: =IF($L9="","",IF(NOT(ISNUMBER($O9)),"要確認：重量が送料表の範囲外",IF(AND($T9>=設定!$C$12,$S9>=設定!$C$13,N($J9)>=設定!$C$14),"◎ 出品候補",IF(AND($T9>=設定!$C$12,$S9>=設定!$C$13),"△ 利益OK・販売実績が不足","× 見送り")))) | X9: =IF($H9="","",INDEX(設定!$C$20:$C$23,MATCH($H9,設定!$A$20:$A$23,0))) | Y9: =IF($H9="","",INDEX(設定!$D$20:$D$23,MATCH($H9,設定!$A$20:$A$23,0))+INDEX(設定!$E$20:$E$23,MATCH($H9,設定!$A$20:$A$23,0)))
A10: 6 | L10: =IF(AND($D10<>"",$F10<>"",$H10<>"",$I10<>""),($F10+N($G10))*設定!$C$4,"") | M10: =IF($L10="","",(($F10+N($G10))*(設定!$C$6+設定!$C$7+設定!$C$9)+設定!$C$8)*設定!$C$4) | N10: =IF($L10="","",($L10-$M10)*設定!$C$10) | O10: =IF($L10="","",IF($I10>MAX(送料表!$B$5:$B$18),"範囲外",INDEX(送料表!$C$5:$F$18,MATCH($I10,送料表!$A$5:$A$18,1),MATCH($H10,送料表!$C$4:$F$4,0)))) | P10: =IF($L10="","",$F10*設定!$C$4*$X10+$Y10) | Q10: =IF($L10="","",設定!$C$11) | R10: =IF(OR($L10="",NOT(ISNUMBER($O10))),"",N($D10)+N($E10)+$M10+$N10+$O10+$P10+$Q10) | S10: =IF($R10="","",$L10-$R10) | T10: =IF(OR($S10="",N($L10)=0),"",$S10/$L10) | U10: =IF(OR($L10="",NOT(ISNUMBER($O10))),"",IF(設定!$C$16-$X10<=0,"設定を確認",MAX((設定!$C$8*設定!$C$4*(1-設定!$C$10)+$Y10+N($D10)+N($E10)+$O10+$Q10-N($G10)*設定!$C$4*設定!$C$16)/(設定!$C$4*(設定!$C$16-$X10)),(設定!$C$8*設定!$C$4*(1-設定!$C$10)+$Y10+N($D10)+N($E10)+$O10+$Q10+設定!$C$13-N($G10)*設定!$C$4*設定!$C$15)/(設定!$C$4*(設定!$C$15-$X10))))) | V10: =IF($L10="","",IF(NOT(ISNUMBER($O10)),"要確認：重量が送料表の範囲外",IF(AND($T10>=設定!$C$12,$S10>=設定!$C$13,N($J10)>=設定!$C$14),"◎ 出品候補",IF(AND($T10>=設定!$C$12,$S10>=設定!$C$13),"△ 利益OK・販売実績が不足","× 見送り")))) | X10: =IF($H10="","",INDEX(設定!$C$20:$C$23,MATCH($H10,設定!$A$20:$A$23,0))) | Y10: =IF($H10="","",INDEX(設定!$D$20:$D$23,MATCH($H10,設定!$A$20:$A$23,0))+INDEX(設定!$E$20:$E$23,MATCH($H10,設定!$A$20:$A$23,0)))
A11: 7 | L11: =IF(AND($D11<>"",$F11<>"",$H11<>"",$I11<>""),($F11+N($G11))*設定!$C$4,"") | M11: =IF($L11="","",(($F11+N($G11))*(設定!$C$6+設定!$C$7+設定!$C$9)+設定!$C$8)*設定!$C$4) | N11: =IF($L11="","",($L11-$M11)*設定!$C$10) | O11: =IF($L11="","",IF($I11>MAX(送料表!$B$5:$B$18),"範囲外",INDEX(送料表!$C$5:$F$18,MATCH($I11,送料表!$A$5:$A$18,1),MATCH($H11,送料表!$C$4:$F$4,0)))) | P11: =IF($L11="","",$F11*設定!$C$4*$X11+$Y11) | Q11: =IF($L11="","",設定!$C$11) | R11: =IF(OR($L11="",NOT(ISNUMBER($O11))),"",N($D11)+N($E11)+$M11+$N11+$O11+$P11+$Q11) | S11: =IF($R11="","",$L11-$R11) | T11: =IF(OR($S11="",N($L11)=0),"",$S11/$L11) | U11: =IF(OR($L11="",NOT(ISNUMBER($O11))),"",IF(設定!$C$16-$X11<=0,"設定を確認",MAX((設定!$C$8*設定!$C$4*(1-設定!$C$10)+$Y11+N($D11)+N($E11)+$O11+$Q11-N($G11)*設定!$C$4*設定!$C$16)/(設定!$C$4*(設定!$C$16-$X11)),(設定!$C$8*設定!$C$4*(1-設定!$C$10)+$Y11+N($D11)+N($E11)+$O11+$Q11+設定!$C$13-N($G11)*設定!$C$4*設定!$C$15)/(設定!$C$4*(設定!$C$15-$X11))))) | V11: =IF($L11="","",IF(NOT(ISNUMBER($O11)),"要確認：重量が送料表の範囲外",IF(AND($T11>=設定!$C$12,$S11>=設定!$C$13,N($J11)>=設定!$C$14),"◎ 出品候補",IF(AND($T11>=設定!$C$12,$S11>=設定!$C$13),"△ 利益OK・販売実績が不足","× 見送り")))) | X11: =IF($H11="","",INDEX(設定!$C$20:$C$23,MATCH($H11,設定!$A$20:$A$23,0))) | Y11: =IF($H11="","",INDEX(設定!$D$20:$D$23,MATCH($H11,設定!$A$20:$A$23,0))+INDEX(設定!$E$20:$E$23,MATCH($H11,設定!$A$20:$A$23,0)))
A12: 8 | L12: =IF(AND($D12<>"",$F12<>"",$H12<>"",$I12<>""),($F12+N($G12))*設定!$C$4,"") | M12: =IF($L12="","",(($F12+N($G12))*(設定!$C$6+設定!$C$7+設定!$C$9)+設定!$C$8)*設定!$C$4) | N12: =IF($L12="","",($L12-$M12)*設定!$C$10) | O12: =IF($L12="","",IF($I12>MAX(送料表!$B$5:$B$18),"範囲外",INDEX(送料表!$C$5:$F$18,MATCH($I12,送料表!$A$5:$A$18,1),MATCH($H12,送料表!$C$4:$F$4,0)))) | P12: =IF($L12="","",$F12*設定!$C$4*$X12+$Y12) | Q12: =IF($L12="","",設定!$C$11) | R12: =IF(OR($L12="",NOT(ISNUMBER($O12))),"",N($D12)+N($E12)+$M12+$N12+$O12+$P12+$Q12) | S12: =IF($R12="","",$L12-$R12) | T12: =IF(OR($S12="",N($L12)=0),"",$S12/$L12) | U12: =IF(OR($L12="",NOT(ISNUMBER($O12))),"",IF(設定!$C$16-$X12<=0,"設定を確認",MAX((設定!$C$8*設定!$C$4*(1-設定!$C$10)+$Y12+N($D12)+N($E12)+$O12+$Q12-N($G12)*設定!$C$4*設定!$C$16)/(設定!$C$4*(設定!$C$16-$X12)),(設定!$C$8*設定!$C$4*(1-設定!$C$10)+$Y12+N($D12)+N($E12)+$O12+$Q12+設定!$C$13-N($G12)*設定!$C$4*設定!$C$15)/(設定!$C$4*(設定!$C$15-$X12))))) | V12: =IF($L12="","",IF(NOT(ISNUMBER($O12)),"要確認：重量が送料表の範囲外",IF(AND($T12>=設定!$C$12,$S12>=設定!$C$13,N($J12)>=設定!$C$14),"◎ 出品候補",IF(AND($T12>=設定!$C$12,$S12>=設定!$C$13),"△ 利益OK・販売実績が不足","× 見送り")))) | X12: =IF($H12="","",INDEX(設定!$C$20:$C$23,MATCH($H12,設定!$A$20:$A$23,0))) | Y12: =IF($H12="","",INDEX(設定!$D$20:$D$23,MATCH($H12,設定!$A$20:$A$23,0))+INDEX(設定!$E$20:$E$23,MATCH($H12,設定!$A$20:$A$23,0)))
A13: 9 | L13: =IF(AND($D13<>"",$F13<>"",$H13<>"",$I13<>""),($F13+N($G13))*設定!$C$4,"") | M13: =IF($L13="","",(($F13+N($G13))*(設定!$C$6+設定!$C$7+設定!$C$9)+設定!$C$8)*設定!$C$4) | N13: =IF($L13="","",($L13-$M13)*設定!$C$10) | O13: =IF($L13="","",IF($I13>MAX(送料表!$B$5:$B$18),"範囲外",INDEX(送料表!$C$5:$F$18,MATCH($I13,送料表!$A$5:$A$18,1),MATCH($H13,送料表!$C$4:$F$4,0)))) | P13: =IF($L13="","",$F13*設定!$C$4*$X13+$Y13) | Q13: =IF($L13="","",設定!$C$11) | R13: =IF(OR($L13="",NOT(ISNUMBER($O13))),"",N($D13)+N($E13)+$M13+$N13+$O13+$P13+$Q13) | S13: =IF($R13="","",$L13-$R13) | T13: =IF(OR($S13="",N($L13)=0),"",$S13/$L13) | U13: =IF(OR($L13="",NOT(ISNUMBER($O13))),"",IF(設定!$C$16-$X13<=0,"設定を確認",MAX((設定!$C$8*設定!$C$4*(1-設定!$C$10)+$Y13+N($D13)+N($E13)+$O13+$Q13-N($G13)*設定!$C$4*設定!$C$16)/(設定!$C$4*(設定!$C$16-$X13)),(設定!$C$8*設定!$C$4*(1-設定!$C$10)+$Y13+N($D13)+N($E13)+$O13+$Q13+設定!$C$13-N($G13)*設定!$C$4*設定!$C$15)/(設定!$C$4*(設定!$C$15-$X13))))) | V13: =IF($L13="","",IF(NOT(ISNUMBER($O13)),"要確認：重量が送料表の範囲外",IF(AND($T13>=設定!$C$12,$S13>=設定!$C$13,N($J13)>=設定!$C$14),"◎ 出品候補",IF(AND($T13>=設定!$C$12,$S13>=設定!$C$13),"△ 利益OK・販売実績が不足","× 見送り")))) | X13: =IF($H13="","",INDEX(設定!$C$20:$C$23,MATCH($H13,設定!$A$20:$A$23,0))) | Y13: =IF($H13="","",INDEX(設定!$D$20:$D$23,MATCH($H13,設定!$A$20:$A$23,0))+INDEX(設定!$E$20:$E$23,MATCH($H13,設定!$A$20:$A$23,0)))
A14: 10 | L14: =IF(AND($D14<>"",$F14<>"",$H14<>"",$I14<>""),($F14+N($G14))*設定!$C$4,"") | M14: =IF($L14="","",(($F14+N($G14))*(設定!$C$6+設定!$C$7+設定!$C$9)+設定!$C$8)*設定!$C$4) | N14: =IF($L14="","",($L14-$M14)*設定!$C$10) | O14: =IF($L14="","",IF($I14>MAX(送料表!$B$5:$B$18),"範囲外",INDEX(送料表!$C$5:$F$18,MATCH($I14,送料表!$A$5:$A$18,1),MATCH($H14,送料表!$C$4:$F$4,0)))) | P14: =IF($L14="","",$F14*設定!$C$4*$X14+$Y14) | Q14: =IF($L14="","",設定!$C$11) | R14: =IF(OR($L14="",NOT(ISNUMBER($O14))),"",N($D14)+N($E14)+$M14+$N14+$O14+$P14+$Q14) | S14: =IF($R14="","",$L14-$R14) | T14: =IF(OR($S14="",N($L14)=0),"",$S14/$L14) | U14: =IF(OR($L14="",NOT(ISNUMBER($O14))),"",IF(設定!$C$16-$X14<=0,"設定を確認",MAX((設定!$C$8*設定!$C$4*(1-設定!$C$10)+$Y14+N($D14)+N($E14)+$O14+$Q14-N($G14)*設定!$C$4*設定!$C$16)/(設定!$C$4*(設定!$C$16-$X14)),(設定!$C$8*設定!$C$4*(1-設定!$C$10)+$Y14+N($D14)+N($E14)+$O14+$Q14+設定!$C$13-N($G14)*設定!$C$4*設定!$C$15)/(設定!$C$4*(設定!$C$15-$X14))))) | V14: =IF($L14="","",IF(NOT(ISNUMBER($O14)),"要確認：重量が送料表の範囲外",IF(AND($T14>=設定!$C$12,$S14>=設定!$C$13,N($J14)>=設定!$C$14),"◎ 出品候補",IF(AND($T14>=設定!$C$12,$S14>=設定!$C$13),"△ 利益OK・販売実績が不足","× 見送り")))) | X14: =IF($H14="","",INDEX(設定!$C$20:$C$23,MATCH($H14,設定!$A$20:$A$23,0))) | Y14: =IF($H14="","",INDEX(設定!$D$20:$D$23,MATCH($H14,設定!$A$20:$A$23,0))+INDEX(設定!$E$20:$E$23,MATCH($H14,設定!$A$20:$A$23,0)))
A15: 11 | L15: =IF(AND($D15<>"",$F15<>"",$H15<>"",$I15<>""),($F15+N($G15))*設定!$C$4,"") | M15: =IF($L15="","",(($F15+N($G15))*(設定!$C$6+設定!$C$7+設定!$C$9)+設定!$C$8)*設定!$C$4) | N15: =IF($L15="","",($L15-$M15)*設定!$C$10) | O15: =IF($L15="","",IF($I15>MAX(送料表!$B$5:$B$18),"範囲外",INDEX(送料表!$C$5:$F$18,MATCH($I15,送料表!$A$5:$A$18,1),MATCH($H15,送料表!$C$4:$F$4,0)))) | P15: =IF($L15="","",$F15*設定!$C$4*$X15+$Y15) | Q15: =IF($L15="","",設定!$C$11) | R15: =IF(OR($L15="",NOT(ISNUMBER($O15))),"",N($D15)+N($E15)+$M15+$N15+$O15+$P15+$Q15) | S15: =IF($R15="","",$L15-$R15) | T15: =IF(OR($S15="",N($L15)=0),"",$S15/$L15) | U15: =IF(OR($L15="",NOT(ISNUMBER($O15))),"",IF(設定!$C$16-$X15<=0,"設定を確認",MAX((設定!$C$8*設定!$C$4*(1-設定!$C$10)+$Y15+N($D15)+N($E15)+$O15+$Q15-N($G15)*設定!$C$4*設定!$C$16)/(設定!$C$4*(設定!$C$16-$X15)),(設定!$C$8*設定!$C$4*(1-設定!$C$10)+$Y15+N($D15)+N($E15)+$O15+$Q15+設定!$C$13-N($G15)*設定!$C$4*設定!$C$15)/(設定!$C$4*(設定!$C$15-$X15))))) | V15: =IF($L15="","",IF(NOT(ISNUMBER($O15)),"要確認：重量が送料表の範囲外",IF(AND($T15>=設定!$C$12,$S15>=設定!$C$13,N($J15)>=設定!$C$14),"◎ 出品候補",IF(AND($T15>=設定!$C$12,$S15>=設定!$C$13),"△ 利益OK・販売実績が不足","× 見送り")))) | X15: =IF($H15="","",INDEX(設定!$C$20:$C$23,MATCH($H15,設定!$A$20:$A$23,0))) | Y15: =IF($H15="","",INDEX(設定!$D$20:$D$23,MATCH($H15,設定!$A$20:$A$23,0))+INDEX(設定!$E$20:$E$23,MATCH($H15,設定!$A$20:$A$23,0)))
A16: 12 | L16: =IF(AND($D16<>"",$F16<>"",$H16<>"",$I16<>""),($F16+N($G16))*設定!$C$4,"") | M16: =IF($L16="","",(($F16+N($G16))*(設定!$C$6+設定!$C$7+設定!$C$9)+設定!$C$8)*設定!$C$4) | N16: =IF($L16="","",($L16-$M16)*設定!$C$10) | O16: =IF($L16="","",IF($I16>MAX(送料表!$B$5:$B$18),"範囲外",INDEX(送料表!$C$5:$F$18,MATCH($I16,送料表!$A$5:$A$18,1),MATCH($H16,送料表!$C$4:$F$4,0)))) | P16: =IF($L16="","",$F16*設定!$C$4*$X16+$Y16) | Q16: =IF($L16="","",設定!$C$11) | R16: =IF(OR($L16="",NOT(ISNUMBER($O16))),"",N($D16)+N($E16)+$M16+$N16+$O16+$P16+$Q16) | S16: =IF($R16="","",$L16-$R16) | T16: =IF(OR($S16="",N($L16)=0),"",$S16/$L16) | U16: =IF(OR($L16="",NOT(ISNUMBER($O16))),"",IF(設定!$C$16-$X16<=0,"設定を確認",MAX((設定!$C$8*設定!$C$4*(1-設定!$C$10)+$Y16+N($D16)+N($E16)+$O16+$Q16-N($G16)*設定!$C$4*設定!$C$16)/(設定!$C$4*(設定!$C$16-$X16)),(設定!$C$8*設定!$C$4*(1-設定!$C$10)+$Y16+N($D16)+N($E16)+$O16+$Q16+設定!$C$13-N($G16)*設定!$C$4*設定!$C$15)/(設定!$C$4*(設定!$C$15-$X16))))) | V16: =IF($L16="","",IF(NOT(ISNUMBER($O16)),"要確認：重量が送料表の範囲外",IF(AND($T16>=設定!$C$12,$S16>=設定!$C$13,N($J16)>=設定!$C$14),"◎ 出品候補",IF(AND($T16>=設定!$C$12,$S16>=設定!$C$13),"△ 利益OK・販売実績が不足","× 見送り")))) | X16: =IF($H16="","",INDEX(設定!$C$20:$C$23,MATCH($H16,設定!$A$20:$A$23,0))) | Y16: =IF($H16="","",INDEX(設定!$D$20:$D$23,MATCH($H16,設定!$A$20:$A$23,0))+INDEX(設定!$E$20:$E$23,MATCH($H16,設定!$A$20:$A$23,0)))
A17: 13 | L17: =IF(AND($D17<>"",$F17<>"",$H17<>"",$I17<>""),($F17+N($G17))*設定!$C$4,"") | M17: =IF($L17="","",(($F17+N($G17))*(設定!$C$6+設定!$C$7+設定!$C$9)+設定!$C$8)*設定!$C$4) | N17: =IF($L17="","",($L17-$M17)*設定!$C$10) | O17: =IF($L17="","",IF($I17>MAX(送料表!$B$5:$B$18),"範囲外",INDEX(送料表!$C$5:$F$18,MATCH($I17,送料表!$A$5:$A$18,1),MATCH($H17,送料表!$C$4:$F$4,0)))) | P17: =IF($L17="","",$F17*設定!$C$4*$X17+$Y17) | Q17: =IF($L17="","",設定!$C$11) | R17: =IF(OR($L17="",NOT(ISNUMBER($O17))),"",N($D17)+N($E17)+$M17+$N17+$O17+$P17+$Q17) | S17: =IF($R17="","",$L17-$R17) | T17: =IF(OR($S17="",N($L17)=0),"",$S17/$L17) | U17: =IF(OR($L17="",NOT(ISNUMBER($O17))),"",IF(設定!$C$16-$X17<=0,"設定を確認",MAX((設定!$C$8*設定!$C$4*(1-設定!$C$10)+$Y17+N($D17)+N($E17)+$O17+$Q17-N($G17)*設定!$C$4*設定!$C$16)/(設定!$C$4*(設定!$C$16-$X17)),(設定!$C$8*設定!$C$4*(1-設定!$C$10)+$Y17+N($D17)+N($E17)+$O17+$Q17+設定!$C$13-N($G17)*設定!$C$4*設定!$C$15)/(設定!$C$4*(設定!$C$15-$X17))))) | V17: =IF($L17="","",IF(NOT(ISNUMBER($O17)),"要確認：重量が送料表の範囲外",IF(AND($T17>=設定!$C$12,$S17>=設定!$C$13,N($J17)>=設定!$C$14),"◎ 出品候補",IF(AND($T17>=設定!$C$12,$S17>=設定!$C$13),"△ 利益OK・販売実績が不足","× 見送り")))) | X17: =IF($H17="","",INDEX(設定!$C$20:$C$23,MATCH($H17,設定!$A$20:$A$23,0))) | Y17: =IF($H17="","",INDEX(設定!$D$20:$D$23,MATCH($H17,設定!$A$20:$A$23,0))+INDEX(設定!$E$20:$E$23,MATCH($H17,設定!$A$20:$A$23,0)))
... A104: 100 | L104: =IF(AND($D104<>"",$F104<>"",$H104<>"",$I104<>""),($F104+N($G104))*設定!$C$4,"") | M104: =IF($L104="","",(($F104+N($G104))*(設定!$C$6+設定!$C$7+設定!$C$9)+設定!$C$8)*設定!$C$4) | N104: =IF($L104="","",($L104-$M104)*設定!$C$10) | O104: =IF($L104="","",IF($I104>MAX(送料表!$B$5:$B$18),"範囲外",INDEX(送料表!$C$5:$F$18,MATCH($I104,送料表!$A$5:$A$18,1),MATCH($H104,送料表!$C$4:$F$4,0)))) | P104: =IF($L104="","",$F104*設定!$C$4*$X104+$Y104) | Q104: =IF($L104="","",設定!$C$11) | R104: =IF(OR($L104="",NOT(ISNUMBER($O104))),"",N($D104)+N($E104)+$M104+$N104+$O104+$P104+$Q104) | S104: =IF($R104="","",$L104-$R104) | T104: =IF(OR($S104="",N($L104)=0),"",$S104/$L104) | U104: =IF(OR($L104="",NOT(ISNUMBER($O104))),"",IF(設定!$C$16-$X104<=0,"設定を確認",MAX((設定!$C$8*設定!$C$4*(1-設定!$C$10)+$Y104+N($D104)+N($E104)+$O104+$Q104-N($G104)*設定!$C$4*設定!$C$16)/(設定!$C$4*(設定!$C$16-$X104)),(設定!$C$8*設定!$C$4*(1-設定!$C$10)+$Y104+N($D104)+N($E104)+$O104+$Q104+設定!$C$13-N($G104)*設定!$C$4*設定!$C$15)/(設定!$C$4*(設定!$C$15-$X104))))) | V104: =IF($L104="","",IF(NOT(ISNUMBER($O104)),"要確認：重量が送料表の範囲外",IF(AND($T104>=設定!$C$12,$S104>=設定!$C$13,N($J104)>=設定!$C$14),"◎ 出品候補",IF(AND($T104>=設定!$C$12,$S104>=設定!$C$13),"△ 利益OK・販売実績が不足","× 見送り")))) | X104: =IF($H104="","",INDEX(設定!$C$20:$C$23,MATCH($H104,設定!$A$20:$A$23,0))) | Y104: =IF($H104="","",INDEX(設定!$D$20:$D$23,MATCH($H104,設定!$A$20:$A$23,0))+INDEX(設定!$E$20:$E$23,MATCH($H104,設定!$A$20:$A$23,0)))

Sheet ショップ分析
A1: ① 売れているショップを見る（3〜5店）
A2: Product Research（Terapeak）で「売れたもの（Sold）」「発送元が日本」に絞り、販売数の多い日本人セラーを記録します。
A4: No | B4: ショップ名（セラーID） | C4: URL | D4: 評価数 | E4: 主なカテゴリー | F4: 売れ筋上位の商品 | G4: 何度も売れている商品 | H4: 似た商品を何種類並べているか | I4: 最近増えた商品 | J4: 気づき・メモ
A5: 1 | B5: （例）japan-goods-xxxx | C5: https://www.ebay.com/str/xxxx | D5: 2500 | E5: キッチン用品・キャラクター雑貨 | F5: キャラ水筒、弁当箱、箸セット | G5: キャラ水筒（色違いで複数回） | H5: 水筒だけで色・容量違い 15種類 | I5: 季節限定デザインの弁当箱 | J5: キャラの日用品を幅広く並べている。容量違いもそれぞれ売れている。
A6: 2
A7: 3
A8: 4
A9: 5
A10: 6
A11: 7
A12: 8
A13: 9
A14: 10
A16: 共通点のまとめ（3〜5店見たら書く）
A17: どのカテゴリーが共通して売れているか
A18: どの価格帯が多いか
A19: 共通する「売れた理由」は何か
A20: 次に候補を広げる元の商品（→「候補展開」へ）

Sheet 候補展開
A1: ② 横・縦・周辺に広げる → ③ 売れた理由で絞る
A2: 1つの売れ筋から20〜30件の候補を出し、元の商品と「売れた理由」が同じものだけ残します。残ったものを「利益計算」に転記します。
A4: No | B4: 元の商品（売れている商品） | C4: 元の商品が売れた理由 | D4: 広げ方 | E4: 広げた種類 | F4: 候補の商品名 | G4: 候補も同じ理由を満たす？ | H4: 直近90日の販売数（件） | I4: 利益計算に転記 | J4: メモ | L4: 広げ方の早見表
A5: 1 | B5: キャラクター水筒 480ml | C5: キャラクター人気 | D5: 横 | E5: 容量違い | F5: 同じキャラの水筒 800ml | G5: ○ | H5: 4 | I5: ○ | L5: 横（同じ商品の別バリエーション） | M5: 縦（同ブランド・同シリーズ） | N5: 周辺（一緒に使うもの）
A6: 2 | B6: キャラクター水筒 480ml | C6: キャラクター人気 | D6: 縦 | E6: 同シリーズ | F6: 同じキャラの弁当箱 | G6: ○ | H6: 6 | I6: ○ | L6: 色違い | M6: 同じブランドの別商品 | N6: 一緒に使う商品
A7: 3 | B7: キャラクター水筒 480ml | C7: キャラクター人気 | D7: 周辺 | E7: 交換品・消耗品 | F7: この水筒の替えパッキン（キャラなし） | G7: × | H7: 2 | J7: キャラ人気が理由なので、キャラなしの部品は優先度を下げる | L7: サイズ違い | M7: 上位モデル | N7: 交換品
A8: 4 | L8: 容量違い | M8: 下位モデル | N8: 消耗品
A9: 5 | L9: 個数違い | M9: 旧モデル | N9: 詰め替え
A10: 6 | L10: セット違い | M10: 新モデル | N10: ケース
A11: 7 | L11: デザイン違い | M11: 同シリーズ | N11: カバー
A12: 8 | L12: キャラクター違い | M12: 同じ価格帯 | N12: アクセサリー
A13: 9 | L13: 季節違い | M13: 高価格帯・低価格帯 | N13: 収納用品
A14: 10 | N14: メンテナンス用品
A15: 11 | N15: ギフト需要の商品
A16: 12
A17: 13
A18: 14
A19: 15
A20: 16
A21: 17
A22: 18
A23: 19
A24: 20
A25: 21
A26: 22
A27: 23
... A204: 200

Sheet 実績記録
A1: 実績記録（毎日つける → 月ごとの時給が出る）
A2: 作業時間も必ず記録します。右の表に月ごとの合計と時給が自動で出ます。
A4: 日付 | B4: 作業時間（h） | C4: 出品数 | D4: 販売数 | E4: 確定利益（円） | F4: メモ | H4: 月 | I4: 作業時間（h） | J4: 出品数 | K4: 販売数 | L4: 確定利益（円） | M4: 時給（円/h） | N4: 計画の目安
A5: 46315 | B5: 2.5 | C5: 0 | D5: 0 | E5: 0 | F5: （例）eBayアカウント作成・古物商許可の書類準備 | H5: 46296 | I5: =SUMIFS($B$5:$B$404,$A$5:$A$404,">="&$H5,$A$5:$A$404,"<"&DATE(YEAR($H5),MONTH($H5)+1,1)) -> 2.5 | J5: =SUMIFS($C$5:$C$404,$A$5:$A$404,">="&$H5,$A$5:$A$404,"<"&DATE(YEAR($H5),MONTH($H5)+1,1)) -> 0 | K5: =SUMIFS($D$5:$D$404,$A$5:$A$404,">="&$H5,$A$5:$A$404,"<"&DATE(YEAR($H5),MONTH($H5)+1,1)) -> 0 | L5: =SUMIFS($E$5:$E$404,$A$5:$A$404,">="&$H5,$A$5:$A$404,"<"&DATE(YEAR($H5),MONTH($H5)+1,1)) -> 0 | M5: =IF(I5=0,"",L5/I5) -> 0 | N5: 1ヶ月目：準備・不用品で最初の売上・評価5〜10件
H6: =DATE(YEAR(H5),MONTH(H5)+1,1) -> 46327 | I6: =SUMIFS($B$5:$B$404,$A$5:$A$404,">="&$H6,$A$5:$A$404,"<"&DATE(YEAR($H6),MONTH($H6)+1,1)) -> 0 | J6: =SUMIFS($C$5:$C$404,$A$5:$A$404,">="&$H6,$A$5:$A$404,"<"&DATE(YEAR($H6),MONTH($H6)+1,1)) -> 0 | K6: =SUMIFS($D$5:$D$404,$A$5:$A$404,">="&$H6,$A$5:$A$404,"<"&DATE(YEAR($H6),MONTH($H6)+1,1)) -> 0 | L6: =SUMIFS($E$5:$E$404,$A$5:$A$404,">="&$H6,$A$5:$A$404,"<"&DATE(YEAR($H6),MONTH($H6)+1,1)) -> 0 | M6: =IF(I6=0,"",L6/I6) | N6: 2ヶ月目
H7: =DATE(YEAR(H6),MONTH(H6)+1,1) -> 46357 | I7: =SUMIFS($B$5:$B$404,$A$5:$A$404,">="&$H7,$A$5:$A$404,"<"&DATE(YEAR($H7),MONTH($H7)+1,1)) -> 0 | J7: =SUMIFS($C$5:$C$404,$A$5:$A$404,">="&$H7,$A$5:$A$404,"<"&DATE(YEAR($H7),MONTH($H7)+1,1)) -> 0 | K7: =SUMIFS($D$5:$D$404,$A$5:$A$404,">="&$H7,$A$5:$A$404,"<"&DATE(YEAR($H7),MONTH($H7)+1,1)) -> 0 | L7: =SUMIFS($E$5:$E$404,$A$5:$A$404,">="&$H7,$A$5:$A$404,"<"&DATE(YEAR($H7),MONTH($H7)+1,1)) -> 0 | M7: =IF(I7=0,"",L7/I7) | N7: 3ヶ月目：月10〜20件販売・月の利益1〜2万円
H8: =DATE(YEAR(H7),MONTH(H7)+1,1) -> 46388 | I8: =SUMIFS($B$5:$B$404,$A$5:$A$404,">="&$H8,$A$5:$A$404,"<"&DATE(YEAR($H8),MONTH($H8)+1,1)) -> 0 | J8: =SUMIFS($C$5:$C$404,$A$5:$A$404,">="&$H8,$A$5:$A$404,"<"&DATE(YEAR($H8),MONTH($H8)+1,1)) -> 0 | K8: =SUMIFS($D$5:$D$404,$A$5:$A$404,">="&$H8,$A$5:$A$404,"<"&DATE(YEAR($H8),MONTH($H8)+1,1)) -> 0 | L8: =SUMIFS($E$5:$E$404,$A$5:$A$404,">="&$H8,$A$5:$A$404,"<"&DATE(YEAR($H8),MONTH($H8)+1,1)) -> 0 | M8: =IF(I8=0,"",L8/I8) | N8: 4ヶ月目
H9: =DATE(YEAR(H8),MONTH(H8)+1,1) -> 46419 | I9: =SUMIFS($B$5:$B$404,$A$5:$A$404,">="&$H9,$A$5:$A$404,"<"&DATE(YEAR($H9),MONTH($H9)+1,1)) -> 0 | J9: =SUMIFS($C$5:$C$404,$A$5:$A$404,">="&$H9,$A$5:$A$404,"<"&DATE(YEAR($H9),MONTH($H9)+1,1)) -> 0 | K9: =SUMIFS($D$5:$D$404,$A$5:$A$404,">="&$H9,$A$5:$A$404,"<"&DATE(YEAR($H9),MONTH($H9)+1,1)) -> 0 | L9: =SUMIFS($E$5:$E$404,$A$5:$A$404,">="&$H9,$A$5:$A$404,"<"&DATE(YEAR($H9),MONTH($H9)+1,1)) -> 0 | M9: =IF(I9=0,"",L9/I9) | N9: 5ヶ月目
H10: =DATE(YEAR(H9),MONTH(H9)+1,1) -> 46447 | I10: =SUMIFS($B$5:$B$404,$A$5:$A$404,">="&$H10,$A$5:$A$404,"<"&DATE(YEAR($H10),MONTH($H10)+1,1)) -> 0 | J10: =SUMIFS($C$5:$C$404,$A$5:$A$404,">="&$H10,$A$5:$A$404,"<"&DATE(YEAR($H10),MONTH($H10)+1,1)) -> 0 | K10: =SUMIFS($D$5:$D$404,$A$5:$A$404,">="&$H10,$A$5:$A$404,"<"&DATE(YEAR($H10),MONTH($H10)+1,1)) -> 0 | L10: =SUMIFS($E$5:$E$404,$A$5:$A$404,">="&$H10,$A$5:$A$404,"<"&DATE(YEAR($H10),MONTH($H10)+1,1)) -> 0 | M10: =IF(I10=0,"",L10/I10) | N10: 6ヶ月目：出品150〜200品・月30件・月の利益4.5万円
H11: =DATE(YEAR(H10),MONTH(H10)+1,1) -> 46478 | I11: =SUMIFS($B$5:$B$404,$A$5:$A$404,">="&$H11,$A$5:$A$404,"<"&DATE(YEAR($H11),MONTH($H11)+1,1)) -> 0 | J11: =SUMIFS($C$5:$C$404,$A$5:$A$404,">="&$H11,$A$5:$A$404,"<"&DATE(YEAR($H11),MONTH($H11)+1,1)) -> 0 | K11: =SUMIFS($D$5:$D$404,$A$5:$A$404,">="&$H11,$A$5:$A$404,"<"&DATE(YEAR($H11),MONTH($H11)+1,1)) -> 0 | L11: =SUMIFS($E$5:$E$404,$A$5:$A$404,">="&$H11,$A$5:$A$404,"<"&DATE(YEAR($H11),MONTH($H11)+1,1)) -> 0 | M11: =IF(I11=0,"",L11/I11) | N11: 7ヶ月目
H12: 合計 | I12: =SUM(I5:I11) -> 2.5 | J12: =SUM(J5:J11) -> 0 | K12: =SUM(K5:K11) -> 0 | L12: =SUM(L5:L11) -> 0 | M12: =IF(I12=0,"",L12/I12) -> 0
H13: ※ 1ヶ月目の月は H5 を変えると、以降の月が自動でずれます。
